pyspat/__init__.py
pyspat/core/__init__.py
pyspat/core/pointpattern.py
pyspat/core/window.py
pyspat/geom/__init__.py
pyspat/geom/distances.py
pyspat/plot/__init__.py
pyspat/plot/ppplot.py
pyspat/sim/__init__.py
pyspat/sim/csr.py
pyspat/stats/__init__.py
pyspat/stats/summary.py
pyspat-0.1.4.dist-info/licenses/LICENCE
pyspat-0.1.4.dist-info/METADATA
pyspat-0.1.4.dist-info/WHEEL
pyspat-0.1.4.dist-info/top_level.txt
pyspat-0.1.4.dist-info/RECORD
