Metadata-Version: 2.4
Name: pyspat
Version: 0.1.4
Summary: Spatial point pattern analysis in Python, inspired by spatstat
Author-email: Jack Peyton <jpeyton01@qub.ac.uk>
License: MIT License
Requires-Python: >=3.8
License-File: LICENCE
Requires-Dist: numpy
Requires-Dist: pandas
Requires-Dist: plotly
Dynamic: license-file
